<?xml version="1.0"?>

<!--
#######################################################################################
##                                                                                   ##
## (c) 2007-2012 Cable Television Laboratories, Inc.  All rights reserved.  Any use  ##
## of this documentation/package is subject to the terms and conditions of the       ##
## CableLabs License provided to you on download of the documentation/package.       ##
##                                                                                   ##
#######################################################################################

 Change History: (Author & Date)
	PCPCII-138 & PCPCII-140- Update the script to match all of the changes made to the D09 version of the
		ATP. (ghassler 07/01/2009 & 08/04/2009)





-->
<pc2xml version="$Revision: 6714 $" 
	name="CODEC-MEDIA_1.7.1" 
	descrip="G.722 (10 msec) UE Termination Session " 
	number="CODEC-MEDIA_1.7.1">
	
	<template file="./templates/CallTermAtUETemp.xml" name="UE1"/>

	<remove_from fsm="UE1">
		<state ID="Setup" sub="prelude"/>
		<state ID="Connected"/>
		<state ID="OnHook"/>
	</remove_from>

	<add_to fsm="UE1">
		<state ID="Setup" sub="prelude">
			<!--  STEP 1 -->
			<start_capture>
				<filter>
					<var_expr>
						<expr>host </expr>
						<msg_ref type="platform">UE0.IP</msg_ref>
						<expr> || host </expr>
						<msg_ref type="platform">Platform.SIP Stack 1 IP Address</msg_ref>
					</var_expr>
				</filter>
			</start_capture>
			
			<!-- STEP 2 -->
			<send protocol="sip" msgtype="Invite">
				<mod modtype="replace" hdr="audio" param="payload-type">
					<expr>98</expr>
				</mod>
				<mod modtype="replace" hdr="ptime" param="value">
					<expr>10</expr>
				</mod>
				<mod modtype="replace" hdr="rtpmap" param="codec-name">
					<expr>G722</expr>
				</mod>
				<mod modtype="replace" hdr="rtpmap" param="payload-type">
					<expr>98</expr>
				</mod>
				<mod modtype="replace" hdr="rtpmap" param="clockrate">
					<expr>64/16000</expr>
				</mod>
				
			</send>
		</state>
		
		<state ID="Connected" timer="30000">
			<prelude once="true">
				<send protocol="sip" msgtype="ACK"/>
			</prelude>
			<response>
				<if>
					<eq>
						<msg_ref type="event"/>
						<expr>DIALOG_CONFIRMED_UAC</expr>
					</eq>
					<then>
						<!-- STEP 2, 3, 4 and 5 -->
						
							<or>
								<and>
									<gt>
										<msg_ref type="sdp" msg_instance="last">18x-Invite.audio.port</msg_ref>
										<expr>0</expr>
									</gt>
									<lt>
										<msg_ref type="sdp" msg_instance="last">18x-Invite.audio.port</msg_ref>
										<expr>65536</expr>
									</lt>
								</and>
								<or>
									<and>
										<gt>
											<msg_ref type="sdp" msg_instance="last">200-UPDATE.audio.port</msg_ref>
											<expr>0</expr>
										</gt>
										<lt>
											<msg_ref type="sdp" msg_instance="last">200-UPDATE.audio.port</msg_ref>
											<expr>65536</expr>
										</lt>
									</and>
									<and>
										<gt>
											<msg_ref type="sdp" msg_instance="last">200-Invite.audio.port</msg_ref>
											<expr>0</expr>
										</gt>
										<lt>
											<msg_ref type="sdp" msg_instance="last">200-Invite.audio.port</msg_ref>
											<expr>65536</expr>
										</lt>
									</and>
								</or>
							</or>
						
						
						<!-- STEP 4 -->
						
							<or>
								<eq>
									<msg_ref type="sdp" msg_instance="last">18x-Invite.audio.protocol</msg_ref>
									<expr>RTP/AVP</expr>
								</eq>
								<or>
									<eq>
										<msg_ref type="sdp" msg_instance="last">200-UPDATE.audio.protocol</msg_ref>
										<expr>RTP/AVP</expr>
									</eq>
									<eq>
										<msg_ref type="sdp" msg_instance="last">200-Invite.audio.protocol</msg_ref>
										<expr>RTP/AVP</expr>
									</eq>
								</or>
							</or>
						
						
						<!-- STEP 5 -->
						<verify step="5" requirements="REQ12630">
							<or>
								<contains>
									<msg_ref type="sdp" msg_instance="last">18x-Invite.audio.payload-type</msg_ref>
									<expr>98</expr>
								</contains>
								<or>
									<contains>
										<msg_ref type="sdp" msg_instance="last">200-UPDATE.audio.payload-type</msg_ref>
										<expr>98</expr>
									</contains>
									<contains>
										<msg_ref type="sdp" msg_instance="last">200-Invite.audio.payload-type</msg_ref>
										<expr>98</expr>
									</contains>
								</or>
							</or>
						</verify>
						
						<verify step="6" requirements="REQ12630, REQ11624">
							<or>
								<eq>
									<msg_ref type="sdp" msg_instance="last">18x-Invite.rtpmap.clockrate</msg_ref>
									<expr>64/16000</expr>
								</eq>
								<or>
									<eq>
										<msg_ref type="sdp" msg_instance="last">200-UPDATE.rtpmap.clockrate</msg_ref>
										<expr>64/16000</expr>
									</eq>
									<eq>
										<msg_ref type="sdp" msg_instance="last">200-Invite.rtpmap.clockrate</msg_ref>
										<expr>64/16000</expr>
									</eq>
								</or>
							</or>
						</verify>
						
						<!-- STEP 8 -->
						<verify step="7" requirements="REQ14825">
							<or>
								<eq>
									<msg_ref type="sdp" msg_instance="last">18x-Invite.ptime.value</msg_ref>
									<expr>10</expr>
								</eq>
								<or>
									<eq>
										<msg_ref type="sdp" msg_instance="last">200-UPDATE.ptime.value</msg_ref>
										<expr>10</expr>
									</eq>
									<eq>
										<msg_ref type="sdp" msg_instance="last">200-Invite.ptime.value</msg_ref>
										<expr>10</expr>
									</eq>
								</or>
							</or>
						</verify>
						
						
					</then>
				</if>
			</response>
			<transition to="Connected" event="OffHookComplete"/>
			<transition to="Releasing" event="TimerExpired"/>
		</state>
		
		<state ID="OnHook">
			<prelude>
				<stop_capture/>
				<send protocol="utility" msgtype="OnHook"/>
			</prelude>
			<postlude>
				<log promptUser="true" verify="true" step="8" 
				expr="Are the RTP packets arriving at approximately 10 msec intervals within the capture file?"/>
			</postlude>				
			<transition to="END" event="OnHookComplete"/>
		</state>
	</add_to>
</pc2xml>
